Workbook

Sheet Revision Plan
A2: SDE 2 LLD revision plan
A4: Start date | B4: 46304 | C4: Assumed start; editable. Calendar days, no skip days. | F4: Recall gap | G4: 3 | H4: Days after completion; reset completed date after recall.
A6: Tasks | B6: =COUNTA('Topic Tracker'!A7:A53) -> 47 | C6: Completed tasks | D6: =COUNTIFS('Topic Tracker'!G7:G53,"Done") -> 0 | E6: Progress | F6: =D6/B6 -> 0 | G6: Planned hours | H6: =SUM('Topic Tracker'!F7:F53)/60 -> 60.166667
A8: Recommended: 21 days. All topics are included. Use 14-day mapping below only if you can sustain the heavier daily load.
A9: Each session: recall first, code one core flow, test edges, then compare variants. Time budgets include review and repairs.
A11: Day | B11: Date | C11: Focus | D11: Hours | E11: Tasks | F11: Done | G11: Progress | H11: Session outcome
A12: 1 | B12: =$B$4+A12-1 -> 46304 | C12: OOP, SOLID and C++ foundations | D12: =SUMIFS('Topic Tracker'!$F$7:$F$53,'Topic Tracker'!$B$7:$B$53,A12)/60 -> 3 | E12: =COUNTIFS('Topic Tracker'!$B$7:$B$53,A12) -> 3 | F12: =COUNTIFS('Topic Tracker'!$B$7:$B$53,A12,'Topic Tracker'!$G$7:$G$53,"Done") -> 0 | G12: =F12/E12 -> 0 | H12: Model before coding; define ownership
A13: 2 | B13: =$B$4+A13-1 -> 46305 | C13: Strategy, DI and factories | D13: =SUMIFS('Topic Tracker'!$F$7:$F$53,'Topic Tracker'!$B$7:$B$53,A13)/60 -> 2.6666667 | E13: =COUNTIFS('Topic Tracker'!$B$7:$B$53,A13) -> 2 | F13: =COUNTIFS('Topic Tracker'!$B$7:$B$53,A13,'Topic Tracker'!$G$7:$G$53,"Done") -> 0 | G13: =F13/E13 -> 0 | H13: Choose and justify replaceable behavior
A14: 3 | B14: =$B$4+A14-1 -> 46306 | C14: State, Chain of Responsibility and ATM | D14: =SUMIFS('Topic Tracker'!$F$7:$F$53,'Topic Tracker'!$B$7:$B$53,A14)/60 -> 2.9166667 | E14: =COUNTIFS('Topic Tracker'!$B$7:$B$53,A14) -> 3 | F14: =COUNTIFS('Topic Tracker'!$B$7:$B$53,A14,'Topic Tracker'!$G$7:$G$53,"Done") -> 0 | G14: =F14/E14 -> 0 | H14: Make transitions and failure paths explicit
A15: 4 | B15: =$B$4+A15-1 -> 46307 | C15: Builder and parking lot | D15: =SUMIFS('Topic Tracker'!$F$7:$F$53,'Topic Tracker'!$B$7:$B$53,A15)/60 -> 2.75 | E15: =COUNTIFS('Topic Tracker'!$B$7:$B$53,A15) -> 2 | F15: =COUNTIFS('Topic Tracker'!$B$7:$B$53,A15,'Topic Tracker'!$G$7:$G$53,"Done") -> 0 | G15: =F15/E15 -> 0 | H15: Allocate real spots; enforce capacity
A16: 5 | B16: =$B$4+A16-1 -> 46308 | C16: Decorator, coffee and Adapter | D16: =SUMIFS('Topic Tracker'!$F$7:$F$53,'Topic Tracker'!$B$7:$B$53,A16)/60 -> 2.8333333 | E16: =COUNTIFS('Topic Tracker'!$B$7:$B$53,A16) -> 3 | F16: =COUNTIFS('Topic Tracker'!$B$7:$B$53,A16,'Topic Tracker'!$G$7:$G$53,"Done") -> 0 | G16: =F16/E16 -> 0 | H16: Compose behavior without class explosion
A17: 6 | B17: =$B$4+A17-1 -> 46309 | C17: Observer, Singleton and logger | D17: =SUMIFS('Topic Tracker'!$F$7:$F$53,'Topic Tracker'!$B$7:$B$53,A17)/60 -> 2.8333333 | E17: =COUNTIFS('Topic Tracker'!$B$7:$B$53,A17) -> 2 | F17: =COUNTIFS('Topic Tracker'!$B$7:$B$53,A17,'Topic Tracker'!$G$7:$G$53,"Done") -> 0 | G17: =F17/E17 -> 0 | H17: Decouple events and destinations
A18: 7 | B18: =$B$4+A18-1 -> 46310 | C18: Tic-tac-toe and snake game | D18: =SUMIFS('Topic Tracker'!$F$7:$F$53,'Topic Tracker'!$B$7:$B$53,A18)/60 -> 2.8333333 | E18: =COUNTIFS('Topic Tracker'!$B$7:$B$53,A18) -> 2 | F18: =COUNTIFS('Topic Tracker'!$B$7:$B$53,A18,'Topic Tracker'!$G$7:$G$53,"Done") -> 0 | G18: =F18/E18 -> 0 | H18: Enforce game invariants and lifetime
A19: 8 | B19: =$B$4+A19-1 -> 46311 | C19: File system, Composite and HashMap | D19: =SUMIFS('Topic Tracker'!$F$7:$F$53,'Topic Tracker'!$B$7:$B$53,A19)/60 -> 2.9166667 | E19: =COUNTIFS('Topic Tracker'!$B$7:$B$53,A19) -> 2 | F19: =COUNTIFS('Topic Tracker'!$B$7:$B$53,A19,'Topic Tracker'!$G$7:$G$53,"Done") -> 0 | G19: =F19/E19 -> 0 | H19: Hierarchy plus data-structure internals
A20: 9 | B20: =$B$4+A20-1 -> 46312 | C20: Command, text editor and chess | D20: =SUMIFS('Topic Tracker'!$F$7:$F$53,'Topic Tracker'!$B$7:$B$53,A20)/60 -> 2.8333333 | E20: =COUNTIFS('Topic Tracker'!$B$7:$B$53,A20) -> 2 | F20: =COUNTIFS('Topic Tracker'!$B$7:$B$53,A20,'Topic Tracker'!$G$7:$G$53,"Done") -> 0 | G20: =F20/E20 -> 0 | H20: Reversible operations and extensibility
A21: 10 | B21: =$B$4+A21-1 -> 46313 | C21: Splitwise, testing and service boundaries | D21: =SUMIFS('Topic Tracker'!$F$7:$F$53,'Topic Tracker'!$B$7:$B$53,A21)/60 -> 2.9166667 | E21: =COUNTIFS('Topic Tracker'!$B$7:$B$53,A21) -> 2 | F21: =COUNTIFS('Topic Tracker'!$B$7:$B$53,A21,'Topic Tracker'!$G$7:$G$53,"Done") -> 0 | G21: =F21/E21 -> 0 | H21: Preserve monetary and balance invariants
A22: 11 | B22: =$B$4+A22-1 -> 46314 | C22: Synchronization and bounded queues | D22: =SUMIFS('Topic Tracker'!$F$7:$F$53,'Topic Tracker'!$B$7:$B$53,A22)/60 -> 2.8333333 | E22: =COUNTIFS('Topic Tracker'!$B$7:$B$53,A22) -> 2 | F22: =COUNTIFS('Topic Tracker'!$B$7:$B$53,A22,'Topic Tracker'!$G$7:$G$53,"Done") -> 0 | G22: =F22/E22 -> 0 | H22: Correct blocking, wakeups and termination
A23: 12 | B23: =$B$4+A23-1 -> 46315 | C23: Futures, thread pool and object pool | D23: =SUMIFS('Topic Tracker'!$F$7:$F$53,'Topic Tracker'!$B$7:$B$53,A23)/60 -> 2.9166667 | E23: =COUNTIFS('Topic Tracker'!$B$7:$B$53,A23) -> 3 | F23: =COUNTIFS('Topic Tracker'!$B$7:$B$53,A23,'Topic Tracker'!$G$7:$G$53,"Done") -> 0 | G23: =F23/E23 -> 0 | H23: Workers and resources have explicit lifecycles
... A32: 21 | B32: =$B$4+A32-1 -> 46324 | C32: Unseen mock and final recall | D32: =SUMIFS('Topic Tracker'!$F$7:$F$53,'Topic Tracker'!$B$7:$B$53,A32)/60 -> 2.75 | E32: =COUNTIFS('Topic Tracker'!$B$7:$B$53,A32) -> 2 | F32: =COUNTIFS('Topic Tracker'!$B$7:$B$53,A32,'Topic Tracker'!$G$7:$G$53,"Done") -> 0 | G32: =F32/E32 -> 0 | H32: Close gaps; explain tradeoffs without notes
A35: 14-day compression
A36: Same tasks and order. Merge sessions; do not remove tests or mocks. Priorities indicate depth, not permission to skip coverage.
A38: Day | B38: Date | C38: 21-day sessions to combine | D38: Hours | E38: Tasks | F38: Done | G38: Progress | H38: Approach
A39: 1 | B39: =$B$4+A39-1 -> 46304 | C39: Day 1 | D39: =SUMIFS('Topic Tracker'!$F$7:$F$53,'Topic Tracker'!$C$7:$C$53,A39)/60 -> 3 | E39: =COUNTIFS('Topic Tracker'!$C$7:$C$53,A39) -> 3 | F39: =COUNTIFS('Topic Tracker'!$C$7:$C$53,A39,'Topic Tracker'!$G$7:$G$53,"Done") -> 0 | G39: =F39/E39 -> 0 | H39: One session; use spare time for recall.
A40: 2 | B40: =$B$4+A40-1 -> 46305 | C40: Day 2 + Day 3 | D40: =SUMIFS('Topic Tracker'!$F$7:$F$53,'Topic Tracker'!$C$7:$C$53,A40)/60 -> 5.5833333 | E40: =COUNTIFS('Topic Tracker'!$C$7:$C$53,A40) -> 5 | F40: =COUNTIFS('Topic Tracker'!$C$7:$C$53,A40,'Topic Tracker'!$G$7:$G$53,"Done") -> 0 | G40: =F40/E40 -> 0 | H40: Split into two blocks with a break.
A41: 3 | B41: =$B$4+A41-1 -> 46306 | C41: Day 4 | D41: =SUMIFS('Topic Tracker'!$F$7:$F$53,'Topic Tracker'!$C$7:$C$53,A41)/60 -> 2.75 | E41: =COUNTIFS('Topic Tracker'!$C$7:$C$53,A41) -> 2 | F41: =COUNTIFS('Topic Tracker'!$C$7:$C$53,A41,'Topic Tracker'!$G$7:$G$53,"Done") -> 0 | G41: =F41/E41 -> 0 | H41: One session; use spare time for recall.
A42: 4 | B42: =$B$4+A42-1 -> 46307 | C42: Day 5 + Day 6 | D42: =SUMIFS('Topic Tracker'!$F$7:$F$53,'Topic Tracker'!$C$7:$C$53,A42)/60 -> 5.6666667 | E42: =COUNTIFS('Topic Tracker'!$C$7:$C$53,A42) -> 5 | F42: =COUNTIFS('Topic Tracker'!$C$7:$C$53,A42,'Topic Tracker'!$G$7:$G$53,"Done") -> 0 | G42: =F42/E42 -> 0 | H42: Split into two blocks with a break.
A43: 5 | B43: =$B$4+A43-1 -> 46308 | C43: Day 7 | D43: =SUMIFS('Topic Tracker'!$F$7:$F$53,'Topic Tracker'!$C$7:$C$53,A43)/60 -> 2.8333333 | E43: =COUNTIFS('Topic Tracker'!$C$7:$C$53,A43) -> 2 | F43: =COUNTIFS('Topic Tracker'!$C$7:$C$53,A43,'Topic Tracker'!$G$7:$G$53,"Done") -> 0 | G43: =F43/E43 -> 0 | H43: One session; use spare time for recall.
A44: 6 | B44: =$B$4+A44-1 -> 46309 | C44: Day 8 | D44: =SUMIFS('Topic Tracker'!$F$7:$F$53,'Topic Tracker'!$C$7:$C$53,A44)/60 -> 2.9166667 | E44: =COUNTIFS('Topic Tracker'!$C$7:$C$53,A44) -> 2 | F44: =COUNTIFS('Topic Tracker'!$C$7:$C$53,A44,'Topic Tracker'!$G$7:$G$53,"Done") -> 0 | G44: =F44/E44 -> 0 | H44: One session; use spare time for recall.
A45: 7 | B45: =$B$4+A45-1 -> 46310 | C45: Day 9 | D45: =SUMIFS('Topic Tracker'!$F$7:$F$53,'Topic Tracker'!$C$7:$C$53,A45)/60 -> 2.8333333 | E45: =COUNTIFS('Topic Tracker'!$C$7:$C$53,A45) -> 2 | F45: =COUNTIFS('Topic Tracker'!$C$7:$C$53,A45,'Topic Tracker'!$G$7:$G$53,"Done") -> 0 | G45: =F45/E45 -> 0 | H45: One session; use spare time for recall.
A46: 8 | B46: =$B$4+A46-1 -> 46311 | C46: Day 10 | D46: =SUMIFS('Topic Tracker'!$F$7:$F$53,'Topic Tracker'!$C$7:$C$53,A46)/60 -> 2.9166667 | E46: =COUNTIFS('Topic Tracker'!$C$7:$C$53,A46) -> 2 | F46: =COUNTIFS('Topic Tracker'!$C$7:$C$53,A46,'Topic Tracker'!$G$7:$G$53,"Done") -> 0 | G46: =F46/E46 -> 0 | H46: One session; use spare time for recall.
A47: 9 | B47: =$B$4+A47-1 -> 46312 | C47: Day 11 | D47: =SUMIFS('Topic Tracker'!$F$7:$F$53,'Topic Tracker'!$C$7:$C$53,A47)/60 -> 2.8333333 | E47: =COUNTIFS('Topic Tracker'!$C$7:$C$53,A47) -> 2 | F47: =COUNTIFS('Topic Tracker'!$C$7:$C$53,A47,'Topic Tracker'!$G$7:$G$53,"Done") -> 0 | G47: =F47/E47 -> 0 | H47: One session; use spare time for recall.
A48: 10 | B48: =$B$4+A48-1 -> 46313 | C48: Day 12 + Day 13 | D48: =SUMIFS('Topic Tracker'!$F$7:$F$53,'Topic Tracker'!$C$7:$C$53,A48)/60 -> 5.8333333 | E48: =COUNTIFS('Topic Tracker'!$C$7:$C$53,A48) -> 5 | F48: =COUNTIFS('Topic Tracker'!$C$7:$C$53,A48,'Topic Tracker'!$G$7:$G$53,"Done") -> 0 | G48: =F48/E48 -> 0 | H48: Split into two blocks with a break.
A49: 11 | B49: =$B$4+A49-1 -> 46314 | C49: Day 14 + Day 15 | D49: =SUMIFS('Topic Tracker'!$F$7:$F$53,'Topic Tracker'!$C$7:$C$53,A49)/60 -> 5.8333333 | E49: =COUNTIFS('Topic Tracker'!$C$7:$C$53,A49) -> 4 | F49: =COUNTIFS('Topic Tracker'!$C$7:$C$53,A49,'Topic Tracker'!$G$7:$G$53,"Done") -> 0 | G49: =F49/E49 -> 0 | H49: Split into two blocks with a break.
A50: 12 | B50: =$B$4+A50-1 -> 46315 | C50: Day 16 + Day 17 | D50: =SUMIFS('Topic Tracker'!$F$7:$F$53,'Topic Tracker'!$C$7:$C$53,A50)/60 -> 5.75 | E50: =COUNTIFS('Topic Tracker'!$C$7:$C$53,A50) -> 4 | F50: =COUNTIFS('Topic Tracker'!$C$7:$C$53,A50,'Topic Tracker'!$G$7:$G$53,"Done") -> 0 | G50: =F50/E50 -> 0 | H50: Split into two blocks with a break.
... A52: 14 | B52: =$B$4+A52-1 -> 46317 | C52: Day 20 + Day 21 | D52: =SUMIFS('Topic Tracker'!$F$7:$F$53,'Topic Tracker'!$C$7:$C$53,A52)/60 -> 5.75 | E52: =COUNTIFS('Topic Tracker'!$C$7:$C$53,A52) -> 4 | F52: =COUNTIFS('Topic Tracker'!$C$7:$C$53,A52,'Topic Tracker'!$G$7:$G$53,"Done") -> 0 | G52: =F52/E52 -> 0 | H52: Split into two blocks with a break.
A55: Readiness rule | C55: Complete the three mocks and repair their missed invariants, tests and ownership issues.
A57: Mock rubric | C57: Clear requirements; cohesive classes; working core flow; edge tests; one justified extension.
A59: Scope | C59: LLD revision only. Continue DSA, HLD and behavioral preparation separately.

Sheet Topic Tracker
A2: Topic progress
A4: Update amber cells. Done = complete the acceptance criterion; initial status is for this new revision cycle.
A5: P0 = master and code; P1 = cover and extend; P2 = bounded review. Revisit completed tasks after 3 days.
A6: ID | B6: 21-day | C6: 14-day | D6: Priority | E6: Topic | F6: Plan min | G6: Status | H6: Completed | I6: Review due | J6: Actual min | K6: Coverage | L6: Acceptance criterion | M6: Repo files | N6: Notes / evidence
A7: T01 | B7: 1 | C7: 1 | D7: P0 | E7: OOP, SOLID and interview structure | F7: 75 | G7: Not started | I7: =IF(H7="","",H7+'Revision Plan'!$G$4) | K7: Add theory | L7: Explain all five SOLID principles with one repo example each. Model entities, associations, composition, invariants and a sequence before coding. | M7: Added revision topic
A8: T02 | B8: 1 | C8: 1 | D8: P0 | E8: C++ ownership and testable interfaces | F8: 75 | G8: Not started | I8: =IF(H8="","",H8+'Revision Plan'!$G$4) | K8: Add theory | L8: Explain virtual destructors, RAII, const/reference semantics and Rule of 0/3/5. Mark owning vs borrowed pointers. Inject Clock, Payment and Repository interfaces. | M8: Added revision topic
A9: T03 | B9: 1 | C9: 1 | D9: P2 | E9: Operator overloading | F9: 30 | G9: Not started | I9: =IF(H9="","",H9+'Revision Plan'!$G$4) | K9: Code present | L9: Reimplement +, +=, == and << with const correctness. Explain value return vs reference return. | M9: Concepts cpp/operatoroverloading.cpp
A10: T04 | B10: 2 | C10: 2 | D10: P0 | E10: Strategy and dependency injection | F10: 80 | G10: Not started | I10: =IF(H10="","",H10+'Revision Plan'!$G$4) | K10: Code present | L10: Write one runtime-swappable strategy from memory. Explain dependency injection vs dependency inversion. Split duplicate examples before compiling. | M10: designpatterns/strategy.cpp designpatterns/strategy2.cpp designpatterns/dependencyingection.cpp
A11: T05 | B11: 2 | C11: 2 | D11: P0 | E11: Factory and Abstract Factory | F11: 80 | G11: Not started | I11: =IF(H11="","",H11+'Revision Plan'!$G$4) | K11: Code present | L11: Create one object vs a family of related objects. Handle unknown types and ownership. Recognize these static factories as simple factories; explain Factory Method. | M11: designpatterns/factory.cpp designpatterns/abstractfactory.cpp practice/rev/factory.cpp
A12: T06 | B12: 3 | C12: 2 | D12: P0 | E12: State and legal transitions | F12: 45 | G12: Not started | I12: =IF(H12="","",H12+'Revision Plan'!$G$4) | K12: Code present | L12: Draw legal transitions and reject illegal operations. Explain when an enum is enough and when polymorphic State helps. | M12: designpatterns/state.cpp designpatterns/statebetter.cpp
A13: T07 | B13: 3 | C13: 2 | D13: P1 | E13: Chain of Responsibility | F13: 30 | G13: Not started | I13: =IF(H13="","",H13+'Revision Plan'!$G$4) | K13: Code present | L13: Initialize the final next handler to nullptr. Test an unhandled request and distinguish alternative handlers from a validation pipeline. | M13: designpatterns/chainofresponsibility.cpp
A14: T08 | B14: 3 | C14: 2 | D14: P0 | E14: ATM machine | F14: 100 | G14: Not started | I14: =IF(H14="","",H14+'Revision Plan'!$G$4) | K14: Code present | L14: Code withdrawal without console I/O in business logic. Validate amount, PIN retries, balance and cash. Failed bank debit must not consume ATM cash. | M14: problems/atmmachine.cpp
A15: T09 | B15: 4 | C15: 3 | D15: P1 | E15: Builder variants | F15: 40 | G15: Not started | I15: =IF(H15="","",H15+'Revision Plan'!$G$4) | K15: Code present | L15: Prefer builderactual.cpp for revision. Explain fluent builder vs director. Keep alternate Desktop examples in separate translation units. | M15: designpatterns/builderactual.cpp designpatterns/builderdp.cpp
A16: T10 | B16: 4 | C16: 3 | D16: P0 | E16: Parking lot | F16: 125 | G16: Not started | I16: =IF(H16="","",H16+'Revision Plan'!$G$4) | K16: Code present | L16: Add actual spot IDs, capacity and allocation/release policy. Calculate fees. Test full lot, duplicate entry and concurrent allocation. Separate appended Ticket variant. | M16: problems/parkinglot.cpp
A17: T11 | B17: 5 | C17: 4 | D17: P0 | E17: Decorator and coffee machine | F17: 100 | G17: Not started | I17: =IF(H17="","",H17+'Revision Plan'!$G$4) | K17: Code present | L17: Compose toppings and numeric prices. Test invalid coffee/payment and repeated selection. Explain decorator ownership. Add dispense failure as a state follow-up. | M17: designpatterns/decorator.cpp problems/coffemachine.cpp
A18: T12 | B18: 5 | C18: 4 | D18: P1 | E18: Adapter | F18: 45 | G18: Not started | I18: =IF(H18="","",H18+'Revision Plan'!$G$4) | K18: Code present | L18: Implement an actual interface translation. Separate the two examples. Explain Adapter vs Decorator. | M18: designpatterns/adapter.cpp
... A53: T47 | B53: 21 | C53: 14 | D53: P0 | E53: Final recall and regression checks | F53: 75 | G53: Not started | I53: =IF(H53="","",H53+'Revision Plan'!$G$4) | K53: Practice | L53: Review all P0 gaps and overdue recall items. Recode the weakest core method and test it. Explain every repo pattern, its alternative and when not to use it. | M53: Added revision topic

Sheet Repo Review
A2: Repository assessment and repair priorities
A4: Priorities reflect prerequisite value and transferability, not measured company question frequency.
A6: Priority | B6: Area | C6: Finding | D6: Action / interpretation | E6: Evidence | F6: Plan day | G6: Type
A7: P0 | B7: Overall assessment | C7: Broad syllabus; uneven implementation quality | D7: Enough breadth for a strong LLD revision base once gaps are repaired. It is not proof of interview readiness. | E7: Static review and C++20 syntax checks; no full runtime/concurrency audit. | F7: All | G7: Assessment
A8: P0 | B8: Compilation baseline | C8: 44 / 52 C++ files pass syntax-only check | D8: 8 fail as whole files: 5 combine examples/variants; 2 miss this capture; Splitwise misses canremove. Separate snippets before treating them as runnable answers. | E8: g++ -std=c++20 -pthread -fsyntax-only; 9 Oct 2026 | F8: 1–21 | G8: Verified
A9: P0 | B9: OOP, SOLID and modeling | C9: Examples exist; no dedicated structured theory guide | D9: Add SRP/OCP/LSP/ISP/DIP, cohesion/coupling, composition vs inheritance, associations and class/sequence sketches. | E9: README is only a title; theory is mostly inline examples. | F9: 1 | G9: Gap
A10: P0 | B10: Testing and boundaries | C10: Demo main() calls; no dedicated automated test suite found | D10: Use assertions, fake Clock/Payment/Repository, invalid-input tests and failure/concurrency tests. Define ownership and exception guarantees. | E10: Tracked-file inventory and reviewed demonstrations. | F10: 1, 10, 20–21 | G10: Gap
A11: P0 | B11: Rate limiter state | C11: Basic implementation mutates copies of user state | D11: Use a reference. Refill from existing tokens and persist timestamps. Sharded token bucket must require >= 1 token, not nonzero. | E11: problems/ratelimiter.cpp:62,96; ratelimiter-sharded.cpp:87 | F11: 14 | G11: Code defect
A12: P0 | B12: Booking expired holds | C12: emplace does not overwrite an existing expired key | D12: Replace or erase/reinsert expired LockInfo. Add an expired-hold reacquisition test; bs.cpp already uses assignment. | E12: problems/bookingsystem.cpp:99 | F12: 15 | G12: Code defect
A13: P0 | B13: Booking atomicity | C13: Individual confirmations can leave partial booking after payment | D13: Use a single all-seats validation/commit boundary, synchronized booking storage, idempotent requests and compensation/reconciliation. | E13: bookingsystem.cpp and bs.cpp: payment precedes per-seat confirm loop. | F13: 15 | G13: Missing follow-up
A14: P0 | B14: Splitwise completion | C14: canremove() undefined; expense/settlement flows unfinished | D14: Complete service APIs, validate split totals, use minor units and define rounding. Test conservation of balances. | E14: problems/splitwise.cpp:231; empty main() | F14: 10 | G14: Compile + incomplete
A15: P0 | B15: Semaphore / blocking queue | C15: Member predicates use [] and read members | D15: Capture this. Add positive-capacity validation and an explicit close contract for blocked producers/consumers. | E15: Concurrency cpp/boundedblockingqueue.cpp:16; semaphore_using_mutex_cv.cpp:19 | F15: 11 | G15: Compile defect
A16: P0 | B16: Producer-consumer shutdown | C16: Consumers loop forever while main joins them | D16: Add closed flag, notify_all and drain/stop policy. Detached consumer variant needs lifetime-safe shutdown too. | E16: producerconsumer.cpp; producerconsumerbetter.cpp; producerconsumer_semaphore.cpp | F16: 11 | G16: Code defect
A17: P0 | B17: Pub/sub destruction order | C17: Subscribers are destroyed before topics finish draining | D17: Explicitly stop/join all topic workers before subscriber destruction. Snapshotting borrowed pointers does not own their lifetime. | E17: problems/pusub.cpp:102–103; reverse member destruction order | F17: 16 | G17: Lifetime risk
... A30: P0 | B30: Interview expectations | C30: Robust code and edge cases matter | D30: Amazon official SDE II guidance emphasizes syntactically correct, robust, well-tested code. This supports prioritizing fixes and tests, not a universal MNC question-frequency ranking. | E30: https://amazon.jobs/content/en/how-we-hire/sde-ii-interview-prep | F30: All | G30: Official source

Sheet File Coverage
A2: Complete source-file coverage
A4: Repository snapshot: 5e716f36cc0815480d0b5346a0233b7bce807e1f (reviewed 9 Oct 2026). All 52 C++ files and all three problem notes are mapped.
A6: Repository path | B6: Topic IDs | C6: 21-day session | D6: C++20 syntax | E6: Inspection note | F6: Pinned source URL
A7: Concepts cpp/operatoroverloading.cpp | B7: T03 | C7: 1 | D7: Pass | E7: Mapped to a topic; passing syntax does not establish correctness. | F7: https://github.com/ksh428/LLD-problems-and-theory/blob/5e716f36cc0815480d0b5346a0233b7bce807e1f/Concepts%20cpp/operatoroverloading.cpp
A8: Concurrency cpp/async.cpp | B8: T26 | C8: 12 | D8: Pass | E8: Mapped to a topic; passing syntax does not establish correctness. | F8: https://github.com/ksh428/LLD-problems-and-theory/blob/5e716f36cc0815480d0b5346a0233b7bce807e1f/Concurrency%20cpp/async.cpp
A9: Concurrency cpp/boundedblockingqueue.cpp | B9: T25 | C9: 11 | D9: Fail | E9: LLD-problems-and-theory/Concurrency cpp/boundedblockingqueue.cpp:16:32: error: ‘this’ was not captured for this lambda function | F9: https://github.com/ksh428/LLD-problems-and-theory/blob/5e716f36cc0815480d0b5346a0233b7bce807e1f/Concurrency%20cpp/boundedblockingqueue.cpp
A10: Concurrency cpp/conditionvariable.cpp | B10: T24 | C10: 11 | D10: Pass | E10: Mapped to a topic; passing syntax does not establish correctness. | F10: https://github.com/ksh428/LLD-problems-and-theory/blob/5e716f36cc0815480d0b5346a0233b7bce807e1f/Concurrency%20cpp/conditionvariable.cpp
A11: Concurrency cpp/conditionvariable2.cpp | B11: T24 | C11: 11 | D11: Pass | E11: Mapped to a topic; passing syntax does not establish correctness. | F11: https://github.com/ksh428/LLD-problems-and-theory/blob/5e716f36cc0815480d0b5346a0233b7bce807e1f/Concurrency%20cpp/conditionvariable2.cpp
A12: Concurrency cpp/objectpool.cpp | B12: T28 | C12: 12 | D12: Pass | E12: Mapped to a topic; passing syntax does not establish correctness. | F12: https://github.com/ksh428/LLD-problems-and-theory/blob/5e716f36cc0815480d0b5346a0233b7bce807e1f/Concurrency%20cpp/objectpool.cpp
A13: Concurrency cpp/producerconsuer2.cpp | B13: T24 | C13: 11 | D13: Pass | E13: Mapped to a topic; passing syntax does not establish correctness. | F13: https://github.com/ksh428/LLD-problems-and-theory/blob/5e716f36cc0815480d0b5346a0233b7bce807e1f/Concurrency%20cpp/producerconsuer2.cpp
A14: Concurrency cpp/producerconsumer.cpp | B14: T24 | C14: 11 | D14: Pass | E14: Mapped to a topic; passing syntax does not establish correctness. | F14: https://github.com/ksh428/LLD-problems-and-theory/blob/5e716f36cc0815480d0b5346a0233b7bce807e1f/Concurrency%20cpp/producerconsumer.cpp
A15: Concurrency cpp/producerconsumer_semaphore.cpp | B15: T25 | C15: 11 | D15: Pass | E15: Mapped to a topic; passing syntax does not establish correctness. | F15: https://github.com/ksh428/LLD-problems-and-theory/blob/5e716f36cc0815480d0b5346a0233b7bce807e1f/Concurrency%20cpp/producerconsumer_semaphore.cpp
A16: Concurrency cpp/producerconsumerbetter.cpp | B16: T24 | C16: 11 | D16: Pass | E16: Mapped to a topic; passing syntax does not establish correctness. | F16: https://github.com/ksh428/LLD-problems-and-theory/blob/5e716f36cc0815480d0b5346a0233b7bce807e1f/Concurrency%20cpp/producerconsumerbetter.cpp
A17: Concurrency cpp/promisefuture.cpp | B17: T26 | C17: 12 | D17: Pass | E17: Mapped to a topic; passing syntax does not establish correctness. | F17: https://github.com/ksh428/LLD-problems-and-theory/blob/5e716f36cc0815480d0b5346a0233b7bce807e1f/Concurrency%20cpp/promisefuture.cpp
... A64: revised-problems.txt | B64: Reference only | C64: Not scheduled | D64: Not applicable | E64: Historical list: 5 marked done; file system/chess/Splitwise TBD. Not carried into new-cycle status. | F64: https://github.com/ksh428/LLD-problems-and-theory/blob/5e716f36cc0815480d0b5346a0233b7bce807e1f/revised-problems.txt
